luckycharms/__init__.py
luckycharms/base.py
luckycharms-0.5.14.dist-info/LICENSE
luckycharms-0.5.14.dist-info/METADATA
luckycharms-0.5.14.dist-info/WHEEL
luckycharms-0.5.14.dist-info/top_level.txt
luckycharms-0.5.14.dist-info/RECORD
